anyblok_delivery/__init__.py
anyblok_delivery/conftest.py
anyblok_delivery/release.py
anyblok_delivery/scripts.py
anyblok_delivery/bloks/__init__.py
anyblok_delivery/bloks/colissimo/__init__.py
anyblok_delivery/bloks/colissimo/address.py
anyblok_delivery/bloks/colissimo/colissimo.py
anyblok_delivery/bloks/colissimo/eventcodes.py
anyblok_delivery/bloks/colissimo/tests/__init__.py
anyblok_delivery/bloks/colissimo/tests/test_model.py
anyblok_delivery/bloks/delivery/__init__.py
anyblok_delivery/bloks/delivery/delivery.py
anyblok_delivery/bloks/delivery/tests/__init__.py
anyblok_delivery/bloks/delivery/tests/test_model.py
anyblok_delivery-1.4.0.dist-info/LICENSE
anyblok_delivery-1.4.0.dist-info/METADATA
anyblok_delivery-1.4.0.dist-info/WHEEL
anyblok_delivery-1.4.0.dist-info/entry_points.txt
anyblok_delivery-1.4.0.dist-info/top_level.txt
anyblok_delivery-1.4.0.dist-info/RECORD
