Metadata-Version: 2.1
Name: anyblok-delivery
Version: 1.4.0
Summary: Carrier delivery management
Home-page: https://github.com/AnyBlok/AnyBlok-Delivery
Author: Franck Bret
Author-email: franckbret@gmail.com
License: UNKNOWN
Keywords: anyblok_delivery
Platform: UNKNOWN
Classifier: Development Status :: 5 - Production/Stable
Classifier: Intended Audience :: Developers
Classifier: Natural Language :: English
Classifier: Programming Language :: Python :: 3
Classifier: Programming Language :: Python :: 3.6
Classifier: Programming Language :: Python :: 3.7
Classifier: Programming Language :: Python :: 3.8
Requires-Dist: anyblok
Requires-Dist: anyblok-address
Requires-Dist: anyblok-attachment
Requires-Dist: anyblok-mixins
Requires-Dist: anyblok-postgres
Requires-Dist: cryptography
Requires-Dist: idna
Requires-Dist: requests
Requires-Dist: requests-toolbelt
